gyat_model/__init__.py
gyat_model/adaline.txt
gyat_model/all.txt
gyat_model/boosting.txt
gyat_model/dimRed.txt
gyat_model/elbowKmeans.txt
gyat_model/intro.txt
gyat_model/logReg.txt
gyat_model/perceptron.txt
gyat_model/perceptronGreDes.txt
gyat_model/prolog8.txt
gyat_model/prologTic.txt
gyat_model/prologWater.txt
gyat_model/randomForest.txt
gyat_model/svm.txt
gyatmodel2-0.1.6.dist-info/licenses/LICENSE
gyatmodel2-0.1.6.dist-info/METADATA
gyatmodel2-0.1.6.dist-info/WHEEL
gyatmodel2-0.1.6.dist-info/top_level.txt
gyatmodel2-0.1.6.dist-info/RECORD
