Metadata-Version: 2.4
Name: gyatModel2
Version: 0.1.6
Summary: A sample package that prints content of AI/ML model text files
Author: Micheal Scofield
Classifier: Programming Language :: Python :: 3
Classifier: Operating System :: OS Independent
Requires-Python: >=3.6
License-File: LICENSE
Dynamic: author
Dynamic: classifier
Dynamic: description
Dynamic: description-content-type
Dynamic: license-file
Dynamic: requires-python
Dynamic: summary
